<keymap version="1" name="Default copy" parent="$default">
  <action id="EditorDown">
    <keyboard-shortcut first-keystroke="down" />
    <keyboard-shortcut first-keystroke="shift alt k" />
  </action>
  <action id="EditorLeft">
    <keyboard-shortcut first-keystroke="left" />
    <keyboard-shortcut first-keystroke="shift alt h" />
  </action>
  <action id="EditorRight">
    <keyboard-shortcut first-keystroke="right" />
    <keyboard-shortcut first-keystroke="shift alt l" />
  </action>
  <action id="EditorUp">
    <keyboard-shortcut first-keystroke="up" />
    <keyboard-shortcut first-keystroke="shift alt j" />
  </action>
  <action id="UnselectPreviousOccurrence" />
  <action id="context.load" />
</keymap>